josiann/__init__.py
josiann/algorithms/__init__.py
josiann/algorithms/map/__init__.py
josiann/algorithms/map/linear.py
josiann/algorithms/map/multicore.py
josiann/algorithms/map/typing.py
josiann/algorithms/map/utils.py
josiann/algorithms/map/vectorized.py
josiann/algorithms/run.py
josiann/algorithms/sequential/__init__.py
josiann/algorithms/sequential/base/__init__.py
josiann/algorithms/sequential/base/compute.py
josiann/algorithms/sequential/base/intialize.py
josiann/algorithms/sequential/base/sa.py
josiann/algorithms/sequential/multicore/__init__.py
josiann/algorithms/sequential/multicore/initialize.py
josiann/algorithms/sequential/multicore/mcsa.py
josiann/algorithms/sequential/vectorized/__init__.py
josiann/algorithms/sequential/vectorized/compute.py
josiann/algorithms/sequential/vectorized/intialize.py
josiann/algorithms/sequential/vectorized/vsa.py
josiann/backup/__init__.py
josiann/backup/backup.py
josiann/backup/multicore.py
josiann/backup/parallel/__init__.py
josiann/backup/parallel/backup.py
josiann/compute.py
josiann/errors.py
josiann/moves/__init__.py
josiann/moves/base.py
josiann/moves/discrete.py
josiann/moves/ensemble.py
josiann/moves/parse.py
josiann/moves/sequential.py
josiann/parallel/__init__.py
josiann/parallel/algorithms/__init__.py
josiann/parallel/algorithms/compute.py
josiann/parallel/algorithms/mappers.py
josiann/parallel/algorithms/psa.py
josiann/parallel/arguments.py
josiann/parallel/moves/__init__.py
josiann/parallel/moves/base.py
josiann/parallel/moves/discrete.py
josiann/py.typed
josiann/storage/__init__.py
josiann/storage/parallel/__init__.py
josiann/storage/parallel/parameters.py
josiann/storage/parallel/trace.py
josiann/storage/parameters.py
josiann/storage/result.py
josiann/storage/trace.py
josiann/typing.py
josiann-1.2.0.dist-info/WHEEL
josiann-1.2.0.dist-info/METADATA
josiann-1.2.0.dist-info/RECORD
