Metadata-Version: 2.3
Name: josiann
Version: 1.2.0
Summary: Simulated Annealing for noisy cost function
Keywords: simulated annealing,optimization,noisy
Author: Matteo Bouvier
Author-email: Matteo Bouvier <<matteo.bouvier@hotmail.fr>>
License: CeCILL-B FREE SOFTWARE LICENSE AGREEMENT
Classifier: Development Status :: 5 - Production/Stable
Classifier: License :: CeCILL-B Free Software License Agreement (CECILL-B)
Classifier: Intended Audience :: Developers
Classifier: Intended Audience :: Science/Research
Classifier: Programming Language :: Python :: 3
Classifier: Programming Language :: Python :: 3.8
Classifier: Programming Language :: Python :: 3.9
Classifier: Programming Language :: Python :: 3.10
Classifier: Topic :: Scientific/Engineering :: Artificial Intelligence
Classifier: Topic :: Scientific/Engineering :: Mathematics
Classifier: Topic :: Utilities
Classifier: Typing :: Typed
Requires-Dist: numpy>=1.26.4
Requires-Dist: attrs>=23.2.0
Requires-Dist: tqdm>=4.66.2
Requires-Dist: sphinx>=7.2.6 ; extra == 'docs'
Requires-Dist: sphinx-autodoc-typehints>=2.0.0 ; extra == 'docs'
Requires-Dist: nbsphinx>=0.9.3 ; extra == 'docs'
Requires-Dist: ipython>=8.22.2 ; extra == 'docs'
Requires-Dist: sphinx-rtd-theme>=2.0.0 ; extra == 'docs'
Requires-Dist: plotly>=5.20.0 ; extra == 'plot'
Requires-Python: >=3.10
Project-URL: Documentation, https://josiann.readthedocs.io/
Project-URL: Source, https://github.com/Vidium/josiann
Provides-Extra: docs
Provides-Extra: plot
